{
  "company_name": "AKTIEBOLAGET SEPARATOR",
  "fiscal_year": 1921,
  "income_statement": {
    "revenue": null,
    "cost_of_goods_sold": null,
    "operating_expenses": null,
    "wages_expense": null,
    "tax_expense": 1493222.05,
    "depreciation": 166551.4,
    "net_income": 988628.88
  },
  "balance_sheet": {
    "total_assets": 100600409.83,
    "current_assets": null,
    "fixed_assets": null,
    "total_liabilities": null,
    "current_liabilities": null,
    "long_term_liabilities": null,
    "shareholders_equity": 84072845.11
  },
  "employees": null,
  "board": null,
  "auditors": [
    {
      "surname": "TRYGGER",
      "first_name": "ERNST",
      "initials": null,
      "auditing_firm": null
    },
    {
      "surname": "JANSSON",
      "first_name": "CARL",
      "initials": null,
      "auditing_firm": null
    },
    {
      "surname": "THIEL",
      "first_name": "ARTHUR",
      "initials": null,
      "auditing_firm": null
    },
    {
      "surname": "FORSBERG",
      "first_name": "ERIK",
      "initials": "AUG.",
      "auditing_firm": null
    },
    {
      "surname": "WÄSTFELT",
      "first_name": "A.",
      "initials": null,
      "auditing_firm": null
    },
    {
      "surname": "BERNSTRÖM",
      "first_name": "ERIK",
      "initials": null,
      "auditing_firm": null
    },
    {
      "surname": "HIRSCH",
      "first_name": "OSCAR",
      "initials": null,
      "auditing_firm": null
    },
    {
      "surname": "LAMM",
      "first_name": "CARL",
      "initials": "ROBERT",
      "auditing_firm": null
    },
    {
      "surname": "STENBECK",
      "first_name": "NILS",
      "initials": null,
      "auditing_firm": null
    }
  ],
  "additional_notes": null
}