{
  "company_name": "Billeruds Aktiebolag",
  "fiscal_year": 1957,
  "income_statement": {
    "revenue": 241.121,
    "cost_of_goods_sold": null,
    "operating_expenses": 192.685,
    "wages_expense": null,
    "tax_expense": null,
    "depreciation": null,
    "net_income": 11.933
  },
  "balance_sheet": {
    "total_assets": 131.575,
    "current_assets": 58.279,
    "fixed_assets": 104.428,
    "total_liabilities": 58.297,
    "current_liabilities": 31.376,
    "long_term_liabilities": 32.581,
    "shareholders_equity": 101.4
  },
  "employees": {
    "n_employees": 6877,
    "n_blue_collar_workers": 6134,
    "n_white_collar_workers": 522
  },
  "board": [
    {
      "surname": "HAMMARSKJÖLD",
      "first_name": "BO",
      "initials": null,
      "position": null
    },
    {
      "surname": "HISING",
      "first_name": "K. I.",
      "initials": null,
      "position": null
    },
    {
      "surname": "CASSEL",
      "first_name": "LEIF",
      "initials": null,
      "position": null
    },
    {
      "surname": "LIEDBERG",
      "first_name": "GÖSTA",
      "initials": null,
      "position": null
    },
    {
      "surname": "SMITH",
      "first_name": "ANDERS",
      "initials": null,
      "position": null
    },
    {
      "surname": "PIHLGREN",
      "first_name": "\nÅKE",
      "initials": null,
      "position": "Verkställande direktör"
    },
    {
      "surname": "THUNHOLM",
      "first_name": "L-E.",
      "initials": null,
      "position": null
    }
  ],
  "auditors": [
    {
      "surname": "ALMQUIST",
      "first_name": "HARRY",
      "initials": null,
      "auditing_firm": "Auktoriserad revisor"
    },
    {
      "surname": "TJUS",
      "first_name": "FRITZ",
      "initials": null,
      "auditing_firm": null
    },
    {
      "surname": "WENDT",
      "first_name": "STELLAN",
      "initials": null,
      "auditing_firm": null
    }
  ],
  "additional_notes": null
}