{
  "company_name": "SVENSKA OLJESLAGERIAKTIEBOLAGET",
  "fiscal_year": 1943,
  "income_statement": {
    "revenue": null,
    "cost_of_goods_sold": null,
    "operating_expenses": null,
    "wages_expense": null,
    "tax_expense": 79381.26,
    "depreciation": 140000.0,
    "net_income": 151418.32
  },
  "balance_sheet": {
    "total_assets": 14619877.27,
    "current_assets": null,
    "fixed_assets": null,
    "total_liabilities": null,
    "current_liabilities": null,
    "long_term_liabilities": null,
    "shareholders_equity": null
  },
  "employees": null,
  "board": [
    {
      "surname": "Persson",
      "first_name": "Ernst",
      "initials": null,
      "position": null
    },
    {
      "surname": "Gullander",
      "first_name": "Oscar",
      "initials": null,
      "position": null
    },
    {
      "surname": "Högberg",
      "first_name": "Eman.",
      "initials": null,
      "position": null
    },
    {
      "surname": "Engberg",
      "first_name": "Gunnar",
      "initials": null,
      "position": null
    },
    {
      "surname": "Sörensen",
      "first_name": null,
      "initials": "S. H.",
      "position": null
    },
    {
      "surname": "Helmerson",
      "first_name": "H.",
      "initials": "H. E.",
      "position": null
    }
  ],
  "auditors": [
    {
      "surname": "Rybeck",
      "first_name": "Ebbe",
      "initials": null,
      "auditing_firm": null
    },
    {
      "surname": "Thufvesson",
      "first_name": "H.",
      "initials": null,
      "auditing_firm": null
    }
  ],
  "additional_notes": null
}