{
  "company_name": "Skandinaviska Kreditaktiebolagets",
  "fiscal_year": 1921,
  "income_statement": {
    "revenue": null,
    "cost_of_goods_sold": null,
    "operating_expenses": 16874811.02,
    "wages_expense": 11897195.89,
    "tax_expense": null,
    "depreciation": 19417447.37,
    "net_income": 18703569.44
  },
  "balance_sheet": {
    "total_assets": 1291332023.61,
    "current_assets": null,
    "fixed_assets": null,
    "total_liabilities": 1082234503.19,
    "current_liabilities": null,
    "long_term_liabilities": null,
    "shareholders_equity": 182000000.0
  },
  "employees": null,
  "board": [
    {
      "surname": "Carlander",
      "first_name": "Axel",
      "initials": null,
      "position": null
    },
    {
      "surname": "Kjellberg",
      "first_name": null,
      "initials": "J. C:son",
      "position": null
    },
    {
      "surname": "Rabe",
      "first_name": null,
      "initials": "P. R.",
      "position": null
    },
    {
      "surname": "Faxe",
      "first_name": "C.",
      "initials": null,
      "position": null
    },
    {
      "surname": "Schmitz",
      "first_name": "Aug.",
      "initials": null,
      "position": null
    },
    {
      "surname": "Zethræus",
      "first_name": "Aug.",
      "initials": null,
      "position": null
    },
    {
      "surname": "Nilsson",
      "first_name": "R.",
      "initials": null,
      "position": null
    },
    {
      "surname": "Broström",
      "first_name": "Dan",
      "initials": null,
      "position": null
    },
    {
      "surname": "Broomé",
      "first_name": "Albert",
      "initials": null,
      "position": null
    },
    {
      "surname": "Strömberg",
      "first_name": null,
      "initials": "O. M.",
      "position": null
    },
    {
      "surname": "Geijer",
      "first_name": "W.",
      "initials": "von",
      "position": null
    },
    {
      "surname": "Skytte",
      "first_name": "W.",
      "initials": null,
      "position": null
    },
    {
      "surname": "Engeström",
      "first_name": "Max",
      "initials": null,
      "position": null
    },
    {
      "surname": "Schwerin",
      "first_name": "Werner",
      "initials": "G. von",
      "position": null
    },
    {
      "surname": "Swartz",
      "first_name": "Carl",
      "initials": null,
      "position": null
    },
    {
      "surname": "Platen",
      "first_name": "Wilhelm",
      "initials": "von",
      "position": null
    },
    {
      "surname": "Mannheimer",
      "first_name": "H.",
      "initials": null,
      "position": null
    },
    {
      "surname": "Hirsch",
      "first_name": "Oscar",
      "initials": null,
      "position": null
    },
    {
      "surname": "Petersson",
      "first_name": "Berndt",
      "initials": null,
      "position": null
    },
    {
      "surname": "Smith",
      "first_name": "Salomon",
      "initials": null,
      "position": null
    },
    {
      "surname": "Lauritzen",
      "first_name": "H.",
      "initials": null,
      "position": null
    },
    {
      "surname": "Wehtje",
      "first_name": "E.",
      "initials": null,
      "position": null
    },
    {
      "surname": "Dillner",
      "first_name": "Gunnar",
      "initials": null,
      "position": null
    },
    {
      "surname": "Hedenlund",
      "first_name": "Ax.",
      "initials": null,
      "position": null
    },
    {
      "surname": "Wingquist",
      "first_name": "Sven",
      "initials": null,
      "position": null
    },
    {
      "surname": "Carleson",
      "first_name": "Conr.",
      "initials": null,
      "position": null
    },
    {
      "surname": "Fahlbeck",
      "first_name": "P.",
      "initials": null,
      "position": null
    },
    {
      "surname": "Faxe",
      "first_name": "L.",
      "initials": null,
      "position": null
    },
    {
      "surname": "Winkler",
      "first_name": "Nils",
      "initials": null,
      "position": null
    },
    {
      "surname": "Nilsson",
      "first_name": "Joh.",
      "initials": null,
      "position": null
    },
    {
      "surname": "Frisell",
      "first_name": "Erik",
      "initials": null,
      "position": null
    },
    {
      "surname": "Ekman",
      "first_name": "Gustaf",
      "initials": null,
      "position": null
    },
    {
      "surname": "Linde",
      "first_name": "Alb.",
      "initials": "Berg von",
      "position": null
    },
    {
      "surname": "Wingårdh",
      "first_name": "August",
      "initials": null,
      "position": null
    },
    {
      "surname": "Ågren",
      "first_name": "Axel",
      "initials": "H.",
      "position": null
    },
    {
      "surname": "Rydbeck",
      "first_name": "O.",
      "initials": null,
      "position": null
    },
    {
      "surname": "Wijk",
      "first_name": "Hjalmar",
      "initials": null,
      "position": null
    },
    {
      "surname": "Lübeck",
      "first_name": "Sven",
      "initials": null,
      "position": null
    },
    {
      "surname": "Dunker",
      "first_name": "Henry",
      "initials": null,
      "position": null
    },
    {
      "surname": "Belfrage",
      "first_name": "Åke",
      "initials": null,
      "position": null
    },
    {
      "surname": "Axelsson",
      "first_name": "S.",
      "initials": null,
      "position": null
    },
    {
      "surname": "Malmros",
      "first_name": "F.",
      "initials": null,
      "position": null
    },
    {
      "surname": "Huldt",
      "first_name": "Kristoffer",
      "initials": null,
      "position": null
    }
  ],
  "auditors": [
    {
      "surname": "Larsson",
      "first_name": "Sigurd",
      "initials": null,
      "auditing_firm": null
    },
    {
      "surname": "Lundberg",
      "first_name": "Gust.",
      "initials": null,
      "auditing_firm": null
    },
    {
      "surname": "Centerwall",
      "first_name": "E.",
      "initials": null,
      "auditing_firm": null
    },
    {
      "surname": "Nilsson",
      "first_name": "Harald",
      "initials": "E.",
      "auditing_firm": null
    }
  ],
  "additional_notes": null
}