{
  "company_name": "Uddeholms Aktiebolag",
  "fiscal_year": 1963,
  "income_statement": {
    "revenue": 595.141,
    "cost_of_goods_sold": 525.302,
    "operating_expenses": null,
    "wages_expense": null,
    "tax_expense": 9.295,
    "depreciation": 46.896,
    "net_income": 14.0
  },
  "balance_sheet": {
    "total_assets": 652.109,
    "current_assets": 296.789,
    "fixed_assets": 350.49,
    "total_liabilities": 338.945,
    "current_liabilities": 78.95,
    "long_term_liabilities": 258.681,
    "shareholders_equity": 298.104
  },
  "employees": {
    "n_employees": 13428,
    "n_blue_collar_workers": null,
    "n_white_collar_workers": null
  },
  "board": [
    {
      "surname": "SCHWARTZ",
      "first_name": null,
      "initials": "C A",
      "position": null
    },
    {
      "surname": "LUNDH",
      "first_name": "Erik",
      "initials": null,
      "position": null
    },
    {
      "surname": "LJUNGDAHL",
      "first_name": null,
      "initials": "K-G",
      "position": null
    },
    {
      "surname": "ÅKERMAN",
      "first_name": "Oskar",
      "initials": null,
      "position": null
    },
    {
      "surname": "WERNER",
      "first_name": "Donovan",
      "initials": null,
      "position": null
    },
    {
      "surname": "LINDAHL",
      "first_name": "Magnus",
      "initials": null,
      "position": null
    },
    {
      "surname": "EKMAN",
      "first_name": "Wilhelm",
      "initials": null,
      "position": "Verkst direktör"
    }
  ],
  "auditors": [
    {
      "surname": "OLSSON",
      "first_name": "Nils",
      "initials": null,
      "auditing_firm": "Aukt revisor"
    },
    {
      "surname": "FRISELL",
      "first_name": null,
      "initials": "G",
      "auditing_firm": "Aukt revisor"
    },
    {
      "surname": "GEIJER",
      "first_name": "Reinh",
      "initials": null,
      "auditing_firm": "Aukt revisor"
    },
    {
      "surname": "UPMARK",
      "first_name": "Gustaf",
      "initials": null,
      "auditing_firm": "Aukt revisor"
    }
  ],
  "additional_notes": null
}